directure/__init__.py
directure/directure.py
directure-0.1.4.dist-info/LICENSE
directure-0.1.4.dist-info/METADATA
directure-0.1.4.dist-info/WHEEL
directure-0.1.4.dist-info/entry_points.txt
directure-0.1.4.dist-info/top_level.txt
directure-0.1.4.dist-info/RECORD
