Metadata-Version: 2.1
Name: directure
Version: 0.1.4
Summary: A tool to explore and visualize directory structures
Home-page: https://github.com/yourusername/directure
Author: Your Name
Author-email: your.email@example.com
License: MIT
Classifier: Programming Language :: Python :: 3
Classifier: License :: OSI Approved :: MIT License
Classifier: Operating System :: OS Independent
Requires-Python: >=3.6
License-File: LICENSE
